[
{
  "type": "text",
  "question": "كم عدد القوائم المالية الرئيسية وفقًا للمعيار المحاسبي الدولي رقم (1)؟",
  "options": [
    "3",
    "4",
    "5",
    "6"
  ],
  "correct": 1
},
{
  "type": "text",
  "question": "أي من القوائم المالية التالية تبين المجموعات الرئيسية للأصول والمطلوبات وحقوق الملكية في فترة زمنية محددة؟",
  "options": [
    "قائمة الدخل",
    "قائمة التدفقات النقدية",
    "قائمة المركز المالي",
    "قائمة التغيرات في حقوق الملكية"
  ],
  "correct": 2
},
{
  "type": "text",
  "question": "أي من القوائم المالية التالية تبين أداء المنشأة ونتيجة العمليات التشغيلية؟",
  "options": [
    "قائمة المركز المالي",
    "قائمة التدفقات النقدية",
    "قائمة التغيرات في حقوق الملكية",
    "قائمة الدخل"
  ],
  "correct": 3
},
{
  "type": "text",
  "question": "أي من القوائم المالية التالية تظهر مبالغ ومصادر التغيرات في حقوق الملكية؟",
  "options": [
    "قائمة المركز المالي",
    "قائمة الدخل",
    "قائمة التغيرات في حقوق الملكية",
    "قائمة التدفقات النقدية"
  ],
  "correct": 2
},
{
  "type": "text",
  "question": "أي من القوائم المالية التالية تبين المقبوضات والمدفوعات النقدية في الفترة التي تحصل فيها هذه التدفقات؟",
  "options": [
    "قائمة المركز المالي",
    "قائمة الدخل",
    "قائمة التغيرات في حقوق الملكية",
    "قائمة التدفقات النقدية"
  ],
  "correct": 3
},
{
  "type": "text",
  "question": "التدفقات النقدية من الأنشطة الاستثمارية تنتج عن:",
  "options": [
    "إصدار الأسهم",
    "توزيع أرباح الأسهم",
    "بيع الممتلكات والمعدات",
    "تسديد ديون"
  ],
  "correct": 2
},
{
  "type": "text",
  "question": "التدفقات النقدية من الأنشطة التمويلية تنتج عن:",
  "options": [
    "بيع الاستثمارات في شركات أخرى",
    "إصدار السندات",
    "شراء أصول ثابتة",
    "بيع أصول ثابتة"
  ],
  "correct": 1
},
{
  "type": "text",
  "question": "التدفقات النقدية من الأنشطة التشغيلية تشمل:",
  "options": [
    "شراء أسهم في شركات أخرى",
    "بيع سندات",
    "المتحصلات النقدية من بيع السلع",
    "شراء مباني"
  ],
  "correct": 2
},
{
  "type": "text",
  "question": "ما هو عنوان المعيار رقم (5) الصادر عن مجلس معايير المحاسبة المالية الأمريكي (FASB)؟",
  "options": [
    "الإيرادات والمصروفات",
    "الأصول والمطلوبات",
    "الاعتراف والقياس في القوائم المالية لمنشآت الأعمال",
    "التدفقات النقدية"
  ],
  "correct": 2
},
{
  "type": "text",
  "question": "ما هي الفروض المحاسبية؟",
  "options": [
    "قوانين يجب إثباتها",
    "جملاً إخبارية يصعب اختبارها",
    "مبادئ محاسبية دقيقة",
    "إجراءات محاسبية محددة"
  ],
  "correct": 1
},
{
  "type": "text",
  "question": "أي مما يلي ليس من الفروض المحاسبية الأساسية؟",
  "options": [
    "استمرارية المشروع",
    "الوحدة المستقلة",
    "الإفصاح التام",
    "النقود كوحدة للقياس"
  ],
  "correct": 2
},
{
  "type": "text",
  "question": "ماذا يعني فرض استقلالية الوحدة الاقتصادية؟",
  "options": [
    "المشروع التجاري غير مسؤول عن ديونه",
    "المشروع التجاري منفصل ومستقل عن ملاك المشروع",
    "المشروع التجاري يمكن أن يندمج مع مشاريع أخرى بسهولة",
    "المشروع التجاري يخضع لنفس القوانين التي يخضع لها ملاكه"
  ],
  "correct": 1
},
{
  "type": "text",
  "question": "ماذا يعني فرض استمرارية المشروع؟",
  "options": [
    "المشروع سينتهي بعد فترة محددة",
    "المشروع مستمر بأعماله العادية إلى وقت غير محدد",
    "المشروع سيحقق أرباحًا دائمًا",
    "المشروع لا يمكن أن يواجه صعوبات مالية"
  ],
  "correct": 1
},
{
  "type": "text",
  "question": "ماذا يعني فرض النقود كوحدة للقياس؟",
  "options": [
    "العمليات تسجل بأي وحدة قياس",
    "العمليات تسجل على أساس الذهب",
    "العمليات تسجل على أساس النقود",
    "العمليات تسجل على أساس القيمة السوقية"
  ],
  "correct": 2
},
{
  "type": "text",
  "question": "ما هو النقد الموجه لفرض النقود كوحدة قياس؟",
  "options": [
    "صعوبة القياس",
    "عدم إمكانية المقارنة",
    "تجاهل التغيرات في القوة الشرائية",
    "عدم وجود معيار موحد"
  ],
  "correct": 2
},
{
  "type": "text",
  "question": "ماذا يعني فرض الفترة المحاسبية؟",
  "options": [
    "تسجيل العمليات في نهاية عمر المشروع",
    "تقسيم حياة المنشأة إلى فترات مالية متساوية",
    "عدم إعداد قوائم مالية دورية",
    "إعداد القوائم المالية مرة واحدة فقط"
  ],
  "correct": 1
},
{
  "type": "text",
  "question": "ما هي العلاقة بين طول الفترة الزمنية ومدى ملائمة المعلومات لاتخاذ القرارات؟",
  "options": [
    "طردية",
    "عكسية",
    "لا توجد علاقة",
    "متقطعة"
  ],
  "correct": 1
},
{
  "type": "text",
  "question": "ما هي العلاقة بين طول الفترة الزمنية ومدى قابلية المعلومات للتحقق والصحة؟",
  "options": [
    "عكسية",
    "طردية",
    "لا توجد علاقة",
    "متقطعة"
  ],
  "correct": 1
},
{
  "type": "text",
  "question": "ما هي المبادئ المحاسبية؟",
  "options": [
    "قوانين ثابتة لا تتغير",
    "تعميمات وإرشادات توجيهية عامة",
    "تفاصيل دقيقة لإثبات العمليات المالية",
    "قواعد محددة يجب اتباعها بحذافيرها"
  ],
  "correct": 1
},
{
  "type": "text",
  "question": "أي مما يلي ليس من المبادئ المحاسبية؟",
  "options": [
    "مبدأ التكلفة التاريخية",
    "مبدأ الاعتراف بالإيراد",
    "مبدأ السرية",
    "مبدأ المقابلة"
  ],
  "correct": 2
},
{
  "type": "text",
  "question": "بموجب مبدأ التكلفة التاريخية، فإن:",
  "options": [
    "الأصل يقيم بالقيمة السوقية الحالية",
    "الأصل يقيم بالتكلفة الأصلية عند الشراء",
    "الأصل يقيم بأعلى القيمتين: التكلفة أو السوق",
    "الأصل يقيم بأقل القيمتين: التكلفة أو السوق"
  ],
  "correct": 1
},
{
  "type": "text",
  "question": "مبدأ الاعتراف بالإيراد يعني أن الإيراد يسجل عندما:",
  "options": [
    "يتم استلام النقد",
    "يتم تقديم الخدمة أو تسليم البضاعة",
    "يتم توقيع العقد",
    "يتم إصدار الفاتورة"
  ],
  "correct": 1
},
{
  "type": "text",
  "question": "ما هما الشرطان الرئيسيان للاعتراف بالإيراد؟",
  "options": [
    "التحقق والتقدير",
    "التحقق والاكتساب",
    "التقدير والاكتمال",
    "الاكتمال والأهمية النسبية"
  ],
  "correct": 1
},
{
  "type": "text",
  "question": "أساس الاستحقاق يعني أن الإيراد يعترف به عندما:",
  "options": [
    "يتم استلام النقد فقط",
    "تنتقل ملكية السلعة أو يتم تقديم الخدمة",
    "يتم إصدار الفاتورة",
    "يتم توقيع العقد"
  ],
  "correct": 1
},
{
  "type": "text",
  "question": "الأساس النقدي يعني أن الإيراد يعترف به عندما:",
  "options": [
    "يتم تقديم الخدمة",
    "تنتقل ملكية السلعة",
    "يتم استلام النقد",
    "يتم توقيع العقد"
  ],
  "correct": 2
},
{
  "type": "text",
  "question": "أي أساس يستخدم عادة في المحاسبة للمهنيين؟",
  "options": [
    "أساس الاستحقاق",
    "الأساس النقدي",
    "أساس التكلفة",
    "أساس القيمة العادلة"
  ],
  "correct": 1
},
{
  "type": "text",
  "question": "مبدأ مقابلة المصروفات بالإيرادات يعني:",
  "options": [
    "تسجيل المصروفات في نفس الفترة التي سجلت فيها الإيرادات المرتبطة بها",
    "تسجيل المصروفات في الفترة التي تم فيها دفعها",
    "تسجيل المصروفات في نهاية السنة المالية",
    "تسجيل المصروفات بأقل قيمة ممكنة"
  ],
  "correct": 0
},
{
  "type": "text",
  "question": "الهدف الرئيسي من مقابلة المصروفات بالإيرادات هو:",
  "options": [
    "زيادة الأرباح",
    "تقليل الضرائب",
    "قياس الأداء (الربح أو الخسارة)",
    "تجميل القوائم المالية"
  ],
  "correct": 2
},
{
  "type": "text",
  "question": "أي مما يلي يمثل صعوبة في تطبيق مبدأ المقابلة؟",
  "options": [
    "سهولة تحديد المصروفات",
    "توقيت تحقق الإيراد",
    "عدم وجود مصروفات",
    "سهولة قياس الإيرادات"
  ],
  "correct": 1
},
{
  "type": "text",
  "question": "مبدأ الإفصاح التام يعني:",
  "options": [
    "إخفاء المعلومات غير الهامة",
    "عرض جميع المعلومات الهامة التي يحتاجها المستخدم",
    "عرض المعلومات بطريقة معقدة",
    "عرض المعلومات فقط للمديرين"
  ],
  "correct": 1
},
{
  "type": "text",
  "question": "الإفصاح التام يهدف إلى:",
  "options": [
    "تضليل المستخدمين",
    "تزويد المعلومات لغرض اتخاذ القرارات",
    "تقليل حجم القوائم المالية",
    "زيادة حجم القوائم المالية"
  ],
  "correct": 1
},
{
  "type": "text",
  "question": "ما هي العلاقة بين المبادئ المحاسبية والفروض المحاسبية؟",
  "options": [
    "المبادئ المحاسبية هي أساس الفروض المحاسبية",
    "الفروض المحاسبية هي أساس المبادئ المحاسبية",
    "لا توجد علاقة بينهما",
    "هما نفس الشيء"
  ],
  "correct": 1
},
{
  "type": "text",
  "question": "إذا تعذر تحديد العلاقة بين المصروف والإيراد، كيف يتم التعامل مع المصروف؟",
  "options": [
    "يتم تجاهله",
    "يتم توزيعه على فترات زمنية بطريقة عقلانية",
    "يتم تحميله على إيرادات الفترة التالية",
    "يتم تحميله بالكامل على إيرادات الفترة الحالية"
  ],
  "correct": 1
},
{
  "type": "text",
  "question": "لماذا يتم تقسيم عمر المشروع إلى فترات محاسبية؟",
  "options": [
    "لتقليل الضرائب",
    "لتسهيل عملية المحاسبة",
    "لمعرفة التغيرات والتطورات التي تطرأ على حقوق المستثمرين",
    "لزيادة الأرباح"
  ],
  "correct": 2
},
{
  "type": "text",
  "question": "أي مما يلي يمثل ميزة لاستخدام التكلفة التاريخية؟",
  "options": [
    "تعكس القيمة الحالية للأصول",
    "سهولة التحقق من صحتها وموضوعيتها",
    "تتجاهل التضخم",
    "تعتمد على الحكم الشخصي"
  ],
  "correct": 1
},
{
  "type": "text",
  "question": "أي مما يلي يعتبر من التدفقات النقدية الداخلة للأنشطة التشغيلية؟",
  "options": [
    "شراء معدات",
    "بيع بضاعة نقدًا",
    "شراء أسهم في شركة أخرى",
    "تسديد قرض"
  ],
  "correct": 1
},
{
  "type": "text",
  "question": "أي مما يلي يعتبر من التدفقات النقدية الخارجة للأنشطة التمويلية؟",
  "options": [
    "شراء مواد خام",
    "بيع أصول ثابتة",
    "دفع أرباح للمساهمين",
    "تحصيل ديون من العملاء"
  ],
  "correct": 2
},
{
  "type": "text",
  "question": "ما هي أهمية قائمة التدفقات النقدية؟",
  "options": [
    "تقييم ربحية الشركة",
    "تقييم قدرة الشركة على توليد النقد",
    "تحديد قيمة أصول الشركة",
    "تحديد حقوق الملكية في الشركة"
  ],
  "correct": 1
},
{
  "type": "text",
  "question": "ما هو تأثير التضخم على استخدام التكلفة التاريخية؟",
  "options": [
    "يزيد من قيمة الأصول",
    "يقلل من قيمة الأصول",
    "يجعل مقارنة القوائم المالية عبر الفترات الزمنية أكثر صعوبة",
    "ليس له تأثير"
  ],
  "correct": 2
},
{
  "type": "text",
  "question": "ما هي أهمية الإفصاح عن السياسات المحاسبية المتبعة؟",
  "options": [
    "لزيادة حجم القوائم المالية",
    "لتمكين المستخدمين من فهم كيفية إعداد القوائم المالية ومقارنتها مع شركات أخرى",
    "لتقليل الضرائب",
    "للامتثال للقوانين واللوائح"
  ],
  "correct": 1
},
{
  "type": "text",
  "question": "ما هي العلاقة بين الربح المحاسبي والربح النقدي؟",
  "options": [
    "هما دائمًا متساويان",
    "الربح المحاسبي يعتمد على أساس الاستحقاق، بينما الربح النقدي يعتمد على التدفقات النقدية",
    "الربح المحاسبي يعتمد على التدفقات النقدية، بينما الربح النقدي يعتمد على أساس الاستحقاق",
    "لا توجد علاقة بينهما"
  ],
  "correct": 1
},
{
  "type": "text",
  "question": "ما هو المقصود بالتحقق في مبدأ الاعتراف بالإيراد؟",
  "options": [
    "التأكد من أن الإيراد قد تم دفعه نقدًا",
    "التأكد من أن الشركة قد قامت بتسليم البضاعة أو تقديم الخدمة",
    "التأكد من وجود دليل موضوعي على وجود الإيراد وقابليته للقياس بشكل موثوق",
    "التأكد من أن الإيراد متوافق مع السياسات المحاسبية للشركة"
  ],
  "correct": 2
},
{
  "type": "text",
  "question": "ما هو المقصود بالاكتساب في مبدأ الاعتراف بالإيراد؟",
  "options": [
    "التأكد من أن الشركة قد استلمت النقد مقابل الإيراد",
    "التأكد من أن الشركة قد قامت بكل ما يلزم لتحقيق الإيراد",
    "التأكد من أن الإيراد متوافق مع القوانين واللوائح",
    "التأكد من أن الإيراد قد تم الإفصاح عنه بشكل كامل في القوائم المالية"
  ],
  "correct": 1
},
{
  "type": "text",
  "question": "ما هي العلاقة بين قائمة الدخل وقائمة المركز المالي؟",
  "options": [
    "لا توجد علاقة بينهما",
    "قائمة الدخل تحدد الأصول والمطلوبات في قائمة المركز المالي",
    "قائمة المركز المالي تحدد الإيرادات والمصروفات في قائمة الدخل",
    "قائمة الدخل تحدد صافي الربح الذي يتم ترحيله إلى حقوق الملكية في قائمة المركز المالي"
  ],
  "correct": 3
},
{
  "type": "text",
  "question": "ما هي العلاقة بين قائمة التدفقات النقدية وقائمة المركز المالي؟",
  "options": [
    "لا توجد علاقة بينهما",
    "قائمة التدفقات النقدية تحدد الأصول والمطلوبات في قائمة المركز المالي",
    "قائمة المركز المالي تحدد التدفقات النقدية في قائمة التدفقات النقدية",
    "قائمة التدفقات النقدية تفسر التغيرات في بعض بنود قائمة المركز المالي، مثل النقد"
  ],
  "correct": 3
},
{
  "type": "text",
  "question": "ما هي أهمية الاحتياطيات في قائمة التغيرات في حقوق الملكية؟",
  "options": [
    "لزيادة الأرباح القابلة للتوزيع",
    "لتغطية الخسائر المستقبلية وتقوية المركز المالي للشركة",
    "لتقليل الضرائب",
    "لزيادة قيمة أسهم الشركة"
  ],
  "correct": 1
},
{
  "type": "text",
  "question": "ما هو الفرق بين الاحتياطي الإجباري والاحتياطي الاختياري؟",
  "options": [
    "الاحتياطي الإجباري يتم تكوينه بقرار من الشركة، بينما الاحتياطي الاختياري يتم تكوينه بموجب القانون",
    "الاحتياطي الإجباري يتم تكوينه بموجب القانون، بينما الاحتياطي الاختياري يتم تكوينه بقرار من الشركة",
    "لا يوجد فرق بينهما",
    "الاحتياطي الإجباري يستخدم لتوزيع الأرباح، بينما الاحتياطي الاختياري يستخدم لتغطية الخسائر"
  ],
  "correct": 1
},
{
  "type": "text",
  "question": "ما هو تأثير توزيع الأرباح على قائمة التغيرات في حقوق الملكية؟",
  "options": [
    "يزيد من حقوق الملكية",
    "يقلل من حقوق الملكية",
    "ليس له تأثير",
    "يزيد من الأرباح المحتجزة"
  ],
  "correct": 1
},
{
  "type": "text",
  "question": "ما هي الأرباح المحتجزة؟",
  "options": [
    "الأرباح التي تم توزيعها على المساهمين",
    "الأرباح التي تم الاحتفاظ بها في الشركة لاستخدامها في المستقبل",
    "الأرباح التي تم دفعها كضرائب",
    "الأرباح التي تم استخدامها لتكوين الاحتياطيات"
  ],
  "correct": 1
},
{
  "type": "text",
  "question": "ما هي أهمية قائمة التغيرات في حقوق الملكية؟",
  "options": [
    "تقييم أداء الشركة",
    "فهم التغيرات التي طرأت على حقوق الملكية وتأثيرها على المساهمين",
    "تحديد قيمة أصول الشركة",
    "تحديد التدفقات النقدية للشركة"
  ],
  "correct": 1
},
{
  "type": "text",
  "question": "أي مما يلي يعتبر من الأصول في قائمة المركز المالي؟",
  "options": [
    "قروض مستحقة الدفع",
    "حسابات دائنة",
    "مخزون",
    "أرباح محتجزة"
  ],
  "correct": 2
},
{
  "type": "text",
  "question": "أي مما يلي يعتبر من المطلوبات في قائمة المركز المالي؟",
  "options": [
    "النقد",
    "حسابات مدينة",
    "معدات",
    "قروض مستحقة الدفع"
  ],
  "correct": 3
},
{
  "type": "text",
  "question": "ما هي المعادلة المحاسبية الأساسية؟",
  "options": [
    "الأصول + المطلوبات = حقوق الملكية",
    "الأصول = المطلوبات + حقوق الملكية",
    "الإيرادات - المصروفات = الأصول",
    "الأصول - المطلوبات = الإيرادات"
  ],
  "correct": 1
},
{
  "type": "text",
  "question": "ما هو الغرض من إعداد القوائم المالية؟",
  "options": [
    "الامتثال للوائح الحكومية فقط",
    "توفير معلومات مفيدة لاتخاذ القرارات الاقتصادية",
    "تضليل المستثمرين",
    "زيادة الضرائب"
  ],
  "correct": 1
},
{
  "type": "text",
  "question": "ما هي أهمية وجود معايير محاسبية موحدة؟",
  "options": [
    "لتقليل الشفافية",
    "لزيادة صعوبة مقارنة القوائم المالية بين الشركات",
    "لضمان الاتساق والموثوقية وقابلية المقارنة في القوائم المالية",
    "لتقليل عدد المحاسبين المطلوبين"
  ],
  "correct": 2
},
{
  "type": "text",
  "question": "أي مما يلي يزيد من حقوق الملكية في قائمة التغيرات في حقوق الملكية؟",
  "options": [
    "توزيع أرباح",
    "تحقيق صافي ربح",
    "شراء أسهم خزينة",
    "تسديد قروض"
  ],
  "correct": 1
},
{
  "type": "text",
  "question": "أي مما يلي يقلل من حقوق الملكية في قائمة التغيرات في حقوق الملكية؟",
  "options": [
    "إصدار أسهم",
    "تحقيق صافي ربح",
    "شراء أسهم خزينة",
    "إعادة تقييم الأصول وزيادة قيمتها"
  ],
  "correct": 2
},
{
  "type": "text",
  "question": "ما هو المقصود بأسهم الخزينة؟",
  "options": [
    "أسهم الشركة التي تحتفظ بها الخزينة العامة للدولة",
    "أسهم الشركة التي أعادت شراءها من السوق",
    "أسهم الشركة المصدرة حديثًا",
    "أسهم الشركة التي تم تخصيصها للموظفين"
  ],
  "correct": 1
},
{
  "type": "text",
  "question": "ما هو تأثير شراء أسهم الخزينة على حقوق الملكية؟",
  "options": [
    "يزيد من حقوق الملكية",
    "يقلل من حقوق الملكية",
    "ليس له تأثير",
    "يزيد من الأرباح المحتجزة"
  ],
  "correct": 1
},
{
  "type": "text",
  "question": "ما هو المقصود بالأصول غير الملموسة؟",
  "options": [
    "الأصول التي ليس لها وجود مادي",
    "الأصول التي يمكن لمسها",
    "الأصول التي يتم استخدامها في الإنتاج",
    "الأصول التي يتم الاحتفاظ بها بغرض البيع"
  ],
  "correct": 0
},
{
  "type": "text",
  "question": "أي مما يلي يعتبر من الأصول غير الملموسة؟",
  "options": [
    "الأراضي",
    "المباني",
    "براءات الاختراع",
    "المخزون"
  ],
  "correct": 2
},
{
  "type": "text",
  "question": "ما هو المقصود بالاستهلاك؟",
  "options": [
    "توزيع تكلفة الأصل الثابت على مدى عمره الإنتاجي",
    "انخفاض قيمة الأصل بسبب التلف أو التقادم",
    "زيادة قيمة الأصل بسبب التضخم",
    "شراء أصول جديدة"
  ],
  "correct": 0
},
{
  "type": "text",
  "question": "ما هو الغرض من الاستهلاك؟",
  "options": [
    "تقليل الضرائب",
    "توزيع تكلفة الأصل على الفترات التي يتم فيها استخدامه لتحقيق الإيراد",
    "زيادة قيمة الأصول",
    "الامتثال للوائح الحكومية"
  ],
  "correct": 1
},
{
  "type": "text",
  "question": "ما هو المقصود بالقيمة الدفترية للأصل؟",
  "options": [
    "تكلفة الأصل الأصلية",
    "تكلفة الأصل الأصلية مطروحًا منها مجمع الاستهلاك",
    "القيمة السوقية الحالية للأصل",
    "القيمة التي يمكن بيع الأصل بها"
  ],
  "correct": 1
},
{
  "type": "text",
  "question": "ما هو المقصود بالالتزامات المتداولة؟",
  "options": [
    "الالتزامات التي يجب سدادها خلال سنة أو دورة التشغيل أيهما أطول",
    "الالتزامات التي يجب سدادها بعد سنة",
    "الالتزامات التي ليس لها تاريخ استحقاق",
    "الالتزامات التي يمكن تحويلها إلى أسهم"
  ],
  "correct": 0
},
{
  "type": "text",
  "question": "أي مما يلي يعتبر من الالتزامات المتداولة؟",
  "options": [
    "القروض طويلة الأجل",
    "حسابات دائنة",
    "السندات",
    "الأسهم الممتازة"
  ],
  "correct": 1
},
{
  "type": "text",
  "question": "ما هو المقصود بالأرباح قبل الفوائد والضرائب (EBIT)؟",
  "options": [
    "صافي الربح بعد الفوائد والضرائب",
    "صافي الربح قبل الفوائد والضرائب",
    "الإيرادات ناقص تكلفة المبيعات",
    "الإيرادات ناقص المصروفات التشغيلية"
  ],
  "correct": 1
},
{
  "type": "text",
  "question": "ما هي أهمية الأرباح قبل الفوائد والضرائب (EBIT)؟",
  "options": [
    "قياس قدرة الشركة على سداد ديونها",
    "قياس ربحية الشركة من عملياتها الأساسية",
    "تحديد قيمة أصول الشركة",
    "تحديد حقوق الملكية في الشركة"
  ],
  "correct": 1
},
{
  "type": "text",
  "question": "ما هو المقصود بالإيرادات الشاملة الأخرى؟",
  "options": [
    "الإيرادات الناتجة عن بيع الأصول الثابتة",
    "الإيرادات الناتجة عن الاستثمارات",
    "الإيرادات التي لا تدخل في تحديد صافي الربح",
    "الإيرادات الناتجة عن العمليات التشغيلية"
  ],
  "correct": 2
},
{
  "type": "text",
  "question": "ما هي أمثلة على الإيرادات الشاملة الأخرى؟",
  "options": [
    "الأرباح والخسائر الناتجة عن ترجمة العملات الأجنبية",
    "الأرباح الناتجة عن بيع البضاعة",
    "الإيرادات الناتجة عن تقديم الخدمات",
    "الأرباح الناتجة عن بيع الأصول الثابتة"
  ],
  "correct": 0
},
{
  "type": "text",
  "question": "يتم إعداد القوائم المالية وفق أعراف ومبادئ متعارف عليها ومقبولة قبولاً عاماً.",
  "options": ["صح", "خطأ"],
  "correct": 0
},
{
  "type": "text",
  "question": "تغطي المبادئ المحاسبية المتعارف عليها مجالات ضيقة في العملية المحاسبية.",
  "options": ["صح", "خطأ"],
  "correct": 1
},
{
  "type": "text",
  "question": "المجموعة الكاملة من القوائم المالية تتضمن 5 قوائم مالية رئيسية.",
  "options": ["صح", "خطأ"],
  "correct": 1
},
{
  "type": "text",
  "question": "قائمة المركز المالي تبين أداء المنشأة.",
  "options": ["صح", "خطأ"],
  "correct": 1
},
{
  "type": "text",
  "question": "قائمة الدخل تعد على أساس الاستحقاق للأرباح.",
  "options": ["صح", "خطأ"],
  "correct": 0
},
{
  "type": "text",
  "question": "قائمة التغيرات في حقوق الملكية تظهر التغيرات التي تحدث على الأصول.",
  "options": ["صح", "خطأ"],
  "correct": 1
},
{
  "type": "text",
  "question": "قائمة التدفقات النقدية تبين المقبوضات والمدفوعات النقدية.",
  "options": ["صح", "خطأ"],
  "correct": 0
},
{
  "type": "text",
  "question": "التدفقات النقدية الاستثمارية تنتج عن إصدار الأسهم.",
  "options": ["صح", "خطأ"],
  "correct": 1
},
{
  "type": "text",
  "question": "التدفقات النقدية التمويلية تنتج عن بيع الممتلكات.",
  "options": ["صح", "خطأ"],
  "correct": 1
},
{
  "type": "text",
  "question": "التدفقات النقدية التشغيلية تمثل التدفقات النقدية المتأتية من الأنشطة المنتجة للإيراد.",
  "options": ["صح", "خطأ"],
  "correct": 0
},
{
  "type": "text",
  "question": "قائمة التدفقات النقدية حلت محل قائمة التغيرات في المركز المالي.",
  "options": ["صح", "خطأ"],
  "correct": 0
},
{
  "type": "text",
  "question": "الفروض المحاسبية هي مسلمات وبديهيات لأغراض إعداد التقارير المالية.",
  "options": ["صح", "خطأ"],
  "correct": 0
},
{
  "type": "text",
  "question": "يمكن اختبار الفروض المحاسبية وإثبات صحتها بسهولة.",
  "options": ["صح", "خطأ"],
  "correct": 1
},
{
  "type": "text",
  "question": "الفروض المحاسبية تعتبر أقل شمولاً من المبادئ المحاسبية.",
  "options": ["صح", "خطأ"],
  "correct": 1
},
{
  "type": "text",
  "question": "استقلالية الوحدة الاقتصادية تعني أن المشروع التجاري منفصل ومستقل عن ملاك المشروع.",
  "options": ["صح", "خطأ"],
  "correct": 0
},
{
  "type": "text",
  "question": "استمرارية المشروع يعني أن المشروع سينتهي بعد فترة محددة.",
  "options": ["صح", "خطأ"],
  "correct": 1
}
]
